raython/__init__.py
raython/utils.py
raython-0.0.1.dist-info/METADATA
raython-0.0.1.dist-info/WHEEL
raython-0.0.1.dist-info/licenses/LICENSE
raython-0.0.1.dist-info/RECORD
